{
    "profile_id": "april-prior-batten-3b71a295",
    "first_name": "April",
    "last_name": "Prior-Batten",
    "sub_title": "Happy days \ud83d\ude03",
    "profile_picture": null,
    "background_image": null,
    "profile_type": "personal",
    "entity_urn": "ACoAABQjlbsBcXQQV9C_3L1S1hISlpdIa4xsi6s",
    "object_urn": 337876411,
    "birth_date": null,
    "summary": "I am passionate and dedicated towards human relations, motivating, and helping others. I am an inducted member in the National Society of Leadership and Success, finished my BBA from Davenport University in Human Resource Management, obtained my certificate of authority license for life insurance, certified profiency of basic knowledge of HRM and landed a temporary assignment with Perrigo's HR Technology department as a production assistant and now a regression testing assistant HRIS/SAP.  Next, took another temporary assignment with Target to support their increased staffing needs at a regional distribution center. Then, took another temporary assignment with Kelly Services to work \"in-house\" as a staffing specialist. Now, currently looking for a full time position within a company that I can grow with and become a valuable asset.\nIn the next five years, I plan to obtain my PHR certification, additional educational credits through SHRM, lean sigma certification, and my MBA in International Business.\n\nI am an expert in customer service. I have experience in staffing, leadership, training, mentoring, coaching, management, sales, marketing, merchandising, human resources, computer skills including Microsoft Word, Excel, PowerPoint, Project and other software such as SAP and Quickbooks, and listed below are numerous other skills and qualifications I possess.",
    "location": {
        "country": "Netherlands",
        "short": "Geldermalsen, Gelderland",
        "city": "Geldermalsen",
        "state": "Gelderland",
        "default": "Geldermalsen, Gelderland, Netherlands"
    },
    "premium": false,
    "influencer": false,
    "treasury_media": [],
    "languages": {
        "primary_locale": {
            "country": "US",
            "language": "en"
        },
        "supported_locales": [
            {
                "country": "US",
                "language": "en"
            }
        ],
        "profile_languages": [
            {
                "name": "English",
                "proficiency": "NATIVE_OR_BILINGUAL"
            },
            {
                "name": "Spanish",
                "proficiency": "ELEMENTARY"
            }
        ]
    },
    "industry": "Human Resources",
    "education": [
        {
            "date": {
                "start": {
                    "month": null,
                    "day": null,
                    "year": 2013
                },
                "end": {
                    "month": null,
                    "day": null,
                    "year": 2015
                }
            },
            "school": {
                "name": "Davenport University",
                "logo": "https://media.licdn.com/dms/image/C560BAQEDkplrZzKFRg/company-logo_400_400/0/1650565209413?e=1703721600&v=beta&t=1jht_y9j378T9fNfScd4Yse0HH5AzM5pQnoywsgJfy8",
                "url": "https://www.linkedin.com/school/davenportuniversity/"
            },
            "degree_name": "Bachelor of Business Administration (BBA)",
            "field_of_study": "Human Resources Management and Services",
            "grade": null
        },
        {
            "date": {
                "start": {
                    "month": null,
                    "day": null,
                    "year": 1999
                },
                "end": {
                    "month": null,
                    "day": null,
                    "year": 2013
                }
            },
            "school": {
                "name": "Kalamazoo Valley Community College",
                "logo": "https://media.licdn.com/dms/image/C560BAQEVcgeva_fKNg/company-logo_400_400/0/1519856134192?e=1703721600&v=beta&t=NspAXioD7NGQtopbtUcuk08mSdCAlKlHlF2i5Pr4k9w",
                "url": "https://www.linkedin.com/school/kalamazoo-valley-community-college/"
            },
            "degree_name": "Associate of Arts (AA)",
            "field_of_study": "Liberal Arts and Sciences, General Studies and Humanities",
            "grade": null
        },
        {
            "date": {
                "start": {
                    "month": null,
                    "day": null,
                    "year": 1998
                },
                "end": {
                    "month": null,
                    "day": null,
                    "year": 1998
                }
            },
            "school": {
                "name": "Wright Beauty Academy  Battle Creek, Michigan",
                "logo": null,
                "url": null
            },
            "degree_name": "Manicurist License",
            "field_of_study": "Nail Technician/Specialist and Manicurist",
            "grade": null
        },
        {
            "date": {
                "start": {
                    "month": null,
                    "day": null,
                    "year": 1997
                },
                "end": {
                    "month": null,
                    "day": null,
                    "year": 1998
                }
            },
            "school": {
                "name": "Kellogg Community College",
                "logo": "https://media.licdn.com/dms/image/C560BAQFKmLHv4gGy2w/company-logo_400_400/0/1655131327730?e=1703721600&v=beta&t=ueMBDI_nFINAIlEKYHREzJxMMaCToueFkczBe47c4Pw",
                "url": "https://www.linkedin.com/school/kellogg-community-college/"
            },
            "degree_name": "Some coursework completed",
            "field_of_study": "Pre-Law Studies",
            "grade": null
        },
        {
            "date": {
                "start": {
                    "month": null,
                    "day": null,
                    "year": 1992
                },
                "end": {
                    "month": null,
                    "day": null,
                    "year": 1996
                }
            },
            "school": {
                "name": "Hastings High School",
                "logo": null,
                "url": null
            },
            "degree_name": "High School",
            "field_of_study": "State Endorsed Diploma in Math, Science, and Reading",
            "grade": null
        }
    ],
    "patents": [],
    "awards": [
        {
            "title": "Foodservice Development Program",
            "description": "-Survivor Syndrome\n-Top 5 Key Company Priorities\n-Foodservice Safety and Tools\n-Financial Review (Sales and Margin Goals, P&L, Bonus)\n-REA and FQI (Relentless Execution Audit and Food Quality Inspection)\n-Foodservice Category Responsibilities and Expectations\n-Hands-on Training\n-Innovations",
            "issuer": "Speedway LLC",
            "date": {
                "month": 7,
                "day": null,
                "year": 2014
            }
        },
        {
            "title": "Inducted Member",
            "description": "Completion of all steps for induction membership such as 3 speaker broadcasts, 3 SNT meetings, and community service hours. Therefore, I obtained my leadership certification and letter of recommendation.",
            "issuer": "National Society of Leadership and Success",
            "date": {
                "month": 7,
                "day": null,
                "year": 2014
            }
        },
        {
            "title": "Leadership Development Program",
            "description": "Class Objectives:\n1) To develop the basic knowledge and skill for Store Management, enabling the manager to be more effective and efficient in meeting their job responsibilities.\n2) To familiarize Store Management with the resources to help them be successful.\n3) To establish the significance of managing a store location profitably, with integrity and emphasizing our goal of providing a Consistent Exceptional Customer Experience.\n4) To provide information and tools that will aid Store Management in focusing their resources towards increasing merchandise sales and margins. This will assist in maximizing bonus potential as well as achieving company goals.\n5) To create an environment where Store Management can learn from each other through an open exchange of ideas and information.\n\n-Safety and Security\n-Customer Service\n-Selling Culture\n-LPBE (Light Product Break Even)\n-Bonus\n-Human Resources/Diversity\n-Leadership",
            "issuer": "Speedway LLC",
            "date": {
                "month": 7,
                "day": null,
                "year": 2014
            }
        }
    ],
    "certifications": [
        {
            "name": "Assurance of Learning",
            "date": {
                "start": {
                    "month": 5,
                    "day": null,
                    "year": 2015
                },
                "end": {
                    "month": null,
                    "day": null,
                    "year": null
                }
            },
            "authority": "The Society of Human Resource Management",
            "url": null,
            "license_number": null,
            "display_source": null,
            "company": null
        },
        {
            "name": "Leadership",
            "date": {
                "start": {
                    "month": 7,
                    "day": null,
                    "year": 2014
                },
                "end": {
                    "month": null,
                    "day": null,
                    "year": null
                }
            },
            "authority": "The National Society of Leadership and Success",
            "url": null,
            "license_number": null,
            "display_source": null,
            "company": {
                "id": null,
                "name": "The National Society of Leadership and Success",
                "logo": "https://media.licdn.com/dms/image/C4E0BAQE462RD2qiqkw/company-logo_400_400/0/1639152335882?e=1703721600&v=beta&t=YaIAOvw1md22IE_p4mBDnUvLex77LI6Qz7EpS4T3_Oc",
                "url": null
            }
        },
        {
            "name": "MI Life Producer License",
            "date": {
                "start": {
                    "month": 6,
                    "day": null,
                    "year": 2014
                },
                "end": {
                    "month": 5,
                    "day": null,
                    "year": 2016
                }
            },
            "authority": "Michigan Department of Insurance and Financial Services (DIFS)",
            "url": "http://www.michigan.gov/difs",
            "license_number": "0684155 (Currently inactive due to conflict of interest with current position)",
            "display_source": "michigan.gov",
            "company": null
        },
        {
            "name": "Manicurist License",
            "date": {
                "start": {
                    "month": 9,
                    "day": null,
                    "year": 1998
                },
                "end": {
                    "month": null,
                    "day": null,
                    "year": null
                }
            },
            "authority": "State of Michigan",
            "url": null,
            "license_number": "2703076617",
            "display_source": null,
            "company": null
        }
    ],
    "organizations": [],
    "projects": [],
    "publications": [],
    "courses": [
        {
            "name": "Accounting Foundations I & II",
            "number": null
        },
        {
            "name": "American Government",
            "number": null
        },
        {
            "name": "Applied Technology",
            "number": null
        },
        {
            "name": "Beginning Spanish",
            "number": null
        },
        {
            "name": "Business Computer Applications",
            "number": null
        },
        {
            "name": "Business Law Foundations",
            "number": null
        },
        {
            "name": "Business Skills for the 21st Century",
            "number": null
        },
        {
            "name": "Children's Literature",
            "number": null
        },
        {
            "name": "College Algebra",
            "number": null
        },
        {
            "name": "Corporate Finance",
            "number": null
        },
        {
            "name": "Creative Writing",
            "number": null
        },
        {
            "name": "Elementary Spanish",
            "number": null
        },
        {
            "name": "English Composition",
            "number": null
        },
        {
            "name": "Fine Arts and Design-Jewelry",
            "number": null
        },
        {
            "name": "Finite Mathematics",
            "number": null
        },
        {
            "name": "Floral Arranging",
            "number": null
        },
        {
            "name": "Foundations of Interpersonal Communications",
            "number": null
        },
        {
            "name": "Fundamentals of Biology",
            "number": null
        },
        {
            "name": "HHS Bar Exam of Law",
            "number": null
        },
        {
            "name": "Home Repair",
            "number": null
        }
    ],
    "test_scores": [],
    "position_groups": [
        {
            "company": {
                "id": 2307,
                "name": "Kelly Services",
                "logo": "https://media.licdn.com/dms/image/D560BAQHlPPE_RTEUiA/company-logo_400_400/0/1666722530512?e=1703721600&v=beta&t=UqV-t0JXdpKkGawiuV3sf5rX3dLEjHabnlXfRMGj3TE",
                "url": "https://www.linkedin.com/company/kellyservices/",
                "employees": {
                    "start": 10001,
                    "end": null
                }
            },
            "date": {
                "start": {
                    "month": 11,
                    "day": null,
                    "year": 2016
                },
                "end": {
                    "month": 12,
                    "day": null,
                    "year": 2016
                }
            },
            "profile_positions": [
                {
                    "location": "Portage, MI",
                    "date": {
                        "start": {
                            "month": 11,
                            "day": null,
                            "year": 2016
                        },
                        "end": {
                            "month": 12,
                            "day": null,
                            "year": 2016
                        }
                    },
                    "company": "Kelly",
                    "description": "Providing Human Resources support to client\u2019s needs such as interviewing, recruiting, sourcing, and onboarding. Other duties include welcoming applicants as well as evaluating and training them to help improve their skills. Ordering background checks and drugs along with other pre-employment screenings.",
                    "title": "Staffing Specialist",
                    "employment_type": null
                }
            ]
        },
        {
            "company": {
                "id": 1512,
                "name": "Target",
                "logo": "https://media.licdn.com/dms/image/C4E0BAQGUjozudTh0yg/company-logo_400_400/0/1519856213195?e=1703721600&v=beta&t=u4t_toalnUTFQao595UySI_oL4tNsT-H8bjLBRHZ6IY",
                "url": "https://www.linkedin.com/company/target/",
                "employees": {
                    "start": 10001,
                    "end": null
                }
            },
            "date": {
                "start": {
                    "month": 2,
                    "day": null,
                    "year": 2016
                },
                "end": {
                    "month": 10,
                    "day": null,
                    "year": 2016
                }
            },
            "profile_positions": [
                {
                    "location": "United States",
                    "date": {
                        "start": {
                            "month": 2,
                            "day": null,
                            "year": 2016
                        },
                        "end": {
                            "month": 10,
                            "day": null,
                            "year": 2016
                        }
                    },
                    "company": "Target",
                    "description": "Providing support to the Human Resource department with many aspects of staffing and onboarding processes including scheduling interviews, new hire orientations, conditional and final job offers, new hire paperwork, and training audits.",
                    "title": "HR Specialist",
                    "employment_type": null
                }
            ]
        },
        {
            "company": {
                "id": 165447,
                "name": "Perrigo Company plc",
                "logo": "https://media.licdn.com/dms/image/C560BAQFgpjyu0zEBmg/company-logo_400_400/0/1656681628111?e=1703721600&v=beta&t=iqUy26VS_ugiCQdmuNAWHWyeiAlQarJ_6Xijqp4bk3M",
                "url": "https://www.linkedin.com/company/perrigo/",
                "employees": {
                    "start": 10001,
                    "end": null
                }
            },
            "date": {
                "start": {
                    "month": 3,
                    "day": null,
                    "year": 2015
                },
                "end": {
                    "month": 1,
                    "day": null,
                    "year": 2016
                }
            },
            "profile_positions": [
                {
                    "location": "Allegan, Michigan",
                    "date": {
                        "start": {
                            "month": 3,
                            "day": null,
                            "year": 2015
                        },
                        "end": {
                            "month": 1,
                            "day": null,
                            "year": 2016
                        }
                    },
                    "company": "Perrigo Company plc",
                    "description": "Providing administrative support and assisting the Human Resource Technology department on all personnel matters of a large company of 11,000+ global employees, regression testing and integrating global HRIS on 10+ countries, validation and payroll processing. Worked on Support Pack Upgrade to HCM and Omega Integration Project. Maintain HCM including SAP/HCM; HCP, HCQ, HCT, ADP, Microsoft Office Suite, SharePoint and Outlook along with many other programs like U Perform, PicPic, and Cisco Jabber. Assists HRT with various projects, duties, receptionist coverage, and many other cross-department functionalities including medical records, LOAs,writing and performing administrative duties with training documents and filing. Perform all personnel actions from hiring to movements to separations along with understanding and implementing the organizational flow chart by building and creating organizational units and positions.",
                    "title": "HR Technology Assistant",
                    "employment_type": null
                }
            ]
        },
        {
            "company": {
                "id": 14182,
                "name": "Davenport University",
                "logo": "https://media.licdn.com/dms/image/C560BAQEDkplrZzKFRg/company-logo_400_400/0/1650565209413?e=1703721600&v=beta&t=1jht_y9j378T9fNfScd4Yse0HH5AzM5pQnoywsgJfy8",
                "url": "https://www.linkedin.com/school/davenportuniversity/",
                "employees": {
                    "start": 1001,
                    "end": 5000
                }
            },
            "date": {
                "start": {
                    "month": 5,
                    "day": null,
                    "year": 2013
                },
                "end": {
                    "month": 4,
                    "day": null,
                    "year": 2015
                }
            },
            "profile_positions": [
                {
                    "location": null,
                    "date": {
                        "start": {
                            "month": 5,
                            "day": null,
                            "year": 2013
                        },
                        "end": {
                            "month": 4,
                            "day": null,
                            "year": 2015
                        }
                    },
                    "company": "Davenport University",
                    "description": "Human Resource Management (BBA)",
                    "title": "Full Time Student",
                    "employment_type": null
                }
            ]
        },
        {
            "company": {
                "id": 4167,
                "name": "PNC",
                "logo": "https://media.licdn.com/dms/image/C4E0BAQGZzrspYyz9oQ/company-logo_400_400/0/1531496983497?e=1703721600&v=beta&t=zQbW2vL1cAUgD_N_t_QRIAGunMjkClw-wYjtKYuzZ80",
                "url": "https://www.linkedin.com/company/pnc-bank/",
                "employees": {
                    "start": 10001,
                    "end": null
                }
            },
            "date": {
                "start": {
                    "month": 12,
                    "day": null,
                    "year": 2014
                },
                "end": {
                    "month": 3,
                    "day": null,
                    "year": 2015
                }
            },
            "profile_positions": [
                {
                    "location": "Kalamazoo, Michigan Area",
                    "date": {
                        "start": {
                            "month": 12,
                            "day": null,
                            "year": 2014
                        },
                        "end": {
                            "month": 3,
                            "day": null,
                            "year": 2015
                        }
                    },
                    "company": "PNC",
                    "description": "Collecting and servicing all assigned accounts on an automated dialer system, which requires knowledge of all databases and legislation and regulations that govern it. Must meet individual and team goals and metrics to have a good scorecard at the end of each month. Performance is graded daily.",
                    "title": "Default Specialist",
                    "employment_type": null
                }
            ]
        },
        {
            "company": {
                "id": 27345,
                "name": "Speedway LLC",
                "logo": "https://media.licdn.com/dms/image/C560BAQG_plsnns2SUg/company-logo_400_400/0/1575727657785?e=1703721600&v=beta&t=0-9qMGYkosyHclRzJz3jw_gwQySk-CuD36Oh5Y8nUUU",
                "url": "https://www.linkedin.com/company/speedway-llc/",
                "employees": {
                    "start": 10001,
                    "end": null
                }
            },
            "date": {
                "start": {
                    "month": 6,
                    "day": null,
                    "year": 2014
                },
                "end": {
                    "month": 8,
                    "day": null,
                    "year": 2014
                }
            },
            "profile_positions": [
                {
                    "location": "Vicksburg, Michigan",
                    "date": {
                        "start": {
                            "month": 7,
                            "day": null,
                            "year": 2014
                        },
                        "end": {
                            "month": 8,
                            "day": null,
                            "year": 2014
                        }
                    },
                    "company": "Speedway LLC",
                    "description": "Basically an assistant manager position since I'm next in line after the store manager. I follow the LAPD philosophy of lead by example, accountability, people development, and delegation.  I have a list of duties and responsibilities I'm required to do on a daily basis",
                    "title": "Shift Leader (officially)",
                    "employment_type": null
                },
                {
                    "location": "Portage, MI",
                    "date": {
                        "start": {
                            "month": 6,
                            "day": null,
                            "year": 2014
                        },
                        "end": {
                            "month": 7,
                            "day": null,
                            "year": 2014
                        }
                    },
                    "company": "Speedway LLC",
                    "description": "Provided customer service direction for a designated shift and team of employees. Trained, coached, and mentored while providing key leadership to employees and fostered an environment focused on customer service and satisfaction. Ordered products, verified deliveries, and posted accurate invoices. Helped ensure all required reports and paperwork are completed in timely fashion. Price checks, date checks, and area pricing surveys and reported results. Demonstrated a high value for Health, Environment, Safety, and Security (HES) issues, initiatives, and programs in both personal and organizational responsibilities. Helped ensure employees follow all Company policies as detailed in the Operations Manual, and in compliance with Federal, State, and local laws. Provides needed assistance in all aspects of store and food operations and holds a key leadership role when the store manager is not on duty.",
                    "title": "Shift Leader Trainee",
                    "employment_type": null
                }
            ]
        },
        {
            "company": {
                "id": null,
                "name": "Encore Floral",
                "logo": null,
                "url": null,
                "employees": {
                    "start": null,
                    "end": null
                }
            },
            "date": {
                "start": {
                    "month": 5,
                    "day": null,
                    "year": 2013
                },
                "end": {
                    "month": 8,
                    "day": null,
                    "year": 2013
                }
            },
            "profile_positions": [
                {
                    "location": null,
                    "date": {
                        "start": {
                            "month": 5,
                            "day": null,
                            "year": 2013
                        },
                        "end": {
                            "month": 8,
                            "day": null,
                            "year": 2013
                        }
                    },
                    "company": "Encore Floral",
                    "description": "Serviced the Kalamazoo/Portage Area including customer service while using excellent communication and problem solving skills. Marketing, Merchandising, Stocking, Inventory Control, Sales and Promotional Sales.",
                    "title": "Floral Merchandiser",
                    "employment_type": null
                }
            ]
        },
        {
            "company": {
                "id": null,
                "name": "MSpa Day Spa and Salon",
                "logo": null,
                "url": null,
                "employees": {
                    "start": null,
                    "end": null
                }
            },
            "date": {
                "start": {
                    "month": 4,
                    "day": null,
                    "year": 1999
                },
                "end": {
                    "month": 11,
                    "day": null,
                    "year": 2012
                }
            },
            "profile_positions": [
                {
                    "location": null,
                    "date": {
                        "start": {
                            "month": 4,
                            "day": null,
                            "year": 1999
                        },
                        "end": {
                            "month": 11,
                            "day": null,
                            "year": 2012
                        }
                    },
                    "company": "MSpa Day Spa and Salon",
                    "description": "Scheduled client appointments and provided excellent customer and personal service to clients, including customer needs assessment, meeting quality standards for services, and evaluation of customer satisfaction. Promoted and selling products and services using well defined marketing strategies. Trained new employees and provided coaching and leadership to other staff members.",
                    "title": "Head Manicurist/Trainer/Department Leader",
                    "employment_type": null
                }
            ]
        }
    ],
    "volunteer_experiences": [
        {
            "date": {
                "start": {
                    "month": 5,
                    "day": null,
                    "year": 2013
                },
                "end": {
                    "month": null,
                    "day": null,
                    "year": null
                }
            },
            "role": "5K Marathon",
            "company": {
                "id": null,
                "name": "Susan G. Komen",
                "logo": "https://media.licdn.com/dms/image/C4E0BAQHg3njUGPbDWQ/company-logo_400_400/0/1519856580338?e=1703721600&v=beta&t=FX-DQsSpszw8l76Y3RLhR48yDUOpPRlD5ek5pFlJa-g",
                "url": "https://www.linkedin.com/company/susangkomen/"
            },
            "cause": "HEALTH",
            "description": "Raised money for breast cancer awareness and prevention and ran the 5K Marathon"
        },
        {
            "date": {
                "start": {
                    "month": 4,
                    "day": null,
                    "year": 2014
                },
                "end": {
                    "month": null,
                    "day": null,
                    "year": null
                }
            },
            "role": "Volunteer to raise money",
            "company": {
                "id": null,
                "name": "Kalamazoo County CAN Council",
                "logo": null,
                "url": null
            },
            "cause": "CHILDREN",
            "description": "Kalamazoo County CAN (Child Abuse and Neglect) council; raised money during Lifesaver Event to help stop child abuse in Kalamazoo County"
        },
        {
            "date": {
                "start": {
                    "month": 5,
                    "day": null,
                    "year": 2013
                },
                "end": {
                    "month": 7,
                    "day": null,
                    "year": 2013
                }
            },
            "role": "Co-Coach",
            "company": {
                "id": null,
                "name": "Vicksburg Little League",
                "logo": null,
                "url": null
            },
            "cause": "CHILDREN",
            "description": "Co-coached girls 11/12 majors softball for the 2013 season."
        },
        {
            "date": {
                "start": {
                    "month": 2,
                    "day": null,
                    "year": 2009
                },
                "end": {
                    "month": null,
                    "day": null,
                    "year": null
                }
            },
            "role": "Nail services",
            "company": {
                "id": null,
                "name": "Krayons 4 Kids",
                "logo": null,
                "url": null
            },
            "cause": "CHILDREN",
            "description": "Volunteer nail services on hospital children on an as needed basis"
        }
    ],
    "skills": [
        "Microsoft Word",
        "Teamwork",
        "Microsoft Excel",
        "PowerPoint",
        "Microsoft Office",
        "Leadership",
        "Research",
        "Customer Service",
        "Positive Can-do Attitude",
        "Problem Solving",
        "HRIS",
        "Product Marketing",
        "Online Advertising",
        "Appointment Scheduling",
        "Logical Thinker",
        "Highly detail oriented",
        "Outstanding interpersonal communication skills",
        "Influence Others",
        "Quick learner",
        "Customer Satisfaction"
    ],
    "network_info": null,
    "related_profiles": null,
    "contact_info": null
}