{
    "profile_id": "bruno-steh",
    "first_name": "Bruno",
    "last_name": "Steh",
    "sub_title": "Cluster Energy Coordinator, DS Smith",
    "profile_picture": null,
    "background_image": "https://media.licdn.com/dms/image/C5616AQHc0okwjky3zg/profile-displaybackgroundimage-shrink_350_1400/0/1517451143971?e=1697673600&v=beta&t=mWP3w0I9UAK5TZkh4ivQ6UbVCZBvgkkVVW9nXmX5zEs",
    "profile_type": "personal",
    "entity_urn": "ACoAABthZicBbarm8aoNy9Q_8uZgFHwPit0NaaU",
    "object_urn": 459367975,
    "birth_date": null,
    "summary": "A creative Engineer, passionate and enthusiastic about the way we people improved and changed our lives with technology. \nIndustry experience in Power Plant Operation, Process Drying and Paper Production. Experience in Project Management - large Biomass Boiler Installation.\nPlayed Tennis on professional level.",
    "location": {
        "country": "Netherlands",
        "short": "Amsterdam Area",
        "city": null,
        "state": null,
        "default": "Amsterdam Area"
    },
    "premium": false,
    "influencer": false,
    "treasury_media": [],
    "languages": {
        "primary_locale": {
            "country": "US",
            "language": "en"
        },
        "supported_locales": [
            {
                "country": "US",
                "language": "en"
            }
        ],
        "profile_languages": [
            {
                "name": "Croatian",
                "proficiency": "PROFESSIONAL_WORKING"
            },
            {
                "name": "English",
                "proficiency": "PROFESSIONAL_WORKING"
            },
            {
                "name": "German",
                "proficiency": "ELEMENTARY"
            },
            {
                "name": "Serbian",
                "proficiency": "PROFESSIONAL_WORKING"
            },
            {
                "name": "Slovenian",
                "proficiency": "NATIVE_OR_BILINGUAL"
            }
        ]
    },
    "industry": "Oil & Energy",
    "education": [
        {
            "date": {
                "start": {
                    "month": null,
                    "day": null,
                    "year": 2015
                },
                "end": {
                    "month": null,
                    "day": null,
                    "year": 2016
                }
            },
            "school": {
                "name": "Cranfield University",
                "logo": "https://media.licdn.com/dms/image/D4E0BAQEJzvWFjsHnaw/company-logo_400_400/0/1663661776454?e=1700697600&v=beta&t=aj2su_rHljnJ2SeiQ_ev8QM9eQ4PphR52uUJ0xIQwC8",
                "url": "https://www.linkedin.com/school/cranfield-university/"
            },
            "degree_name": "Master of Science (MSc)",
            "field_of_study": "Energy Systems and Thermal processes"
        },
        {
            "date": {
                "start": {
                    "month": null,
                    "day": null,
                    "year": 2014
                },
                "end": {
                    "month": null,
                    "day": null,
                    "year": 2017
                }
            },
            "school": {
                "name": "University of Ljubljana",
                "logo": "https://media.licdn.com/dms/image/C4E0BAQHdxBNw24QZXw/company-logo_400_400/0/1593587187514?e=1700697600&v=beta&t=wDnQcbU7p8MtwdAbJXOmvYDGtrq7xlXTJwtfv45ev3Y",
                "url": "https://www.linkedin.com/school/university-of-ljubljana/"
            },
            "degree_name": "Master of Science (MSc)",
            "field_of_study": "Power and Process Engineering"
        },
        {
            "date": {
                "start": {
                    "month": null,
                    "day": null,
                    "year": 2011
                },
                "end": {
                    "month": null,
                    "day": null,
                    "year": 2014
                }
            },
            "school": {
                "name": "University of Ljubljana, Faculty of Mechanical engineering",
                "logo": null,
                "url": null
            },
            "degree_name": "Bachelor's degree",
            "field_of_study": "Mechanical Engineering"
        }
    ],
    "patents": [],
    "awards": [],
    "certifications": [],
    "organizations": [],
    "projects": [
        {
            "title": "Empirical models for forecasting consumption in district heating",
            "date": {
                "start": {
                    "month": 1,
                    "day": null,
                    "year": 2015
                },
                "end": {
                    "month": 3,
                    "day": null,
                    "year": 2015
                }
            },
            "description": null,
            "contributors": [
                {
                    "type": "standardizedContributor",
                    "first_name": "Bruno",
                    "last_name": "Steh",
                    "name": null,
                    "headline": "Cluster Energy Coordinator, DS Smith"
                },
                {
                    "type": "nonStandardizedContributor",
                    "first_name": null,
                    "last_name": null,
                    "name": "Ziga Begelj",
                    "headline": null
                },
                {
                    "type": "nonStandardizedContributor",
                    "first_name": null,
                    "last_name": null,
                    "name": "Primoz Potocnik",
                    "headline": null
                }
            ]
        },
        {
            "title": "Polymer materials for fuel pumps",
            "date": {
                "start": {
                    "month": 4,
                    "day": null,
                    "year": 2014
                },
                "end": {
                    "month": 10,
                    "day": null,
                    "year": 2014
                }
            },
            "description": null,
            "contributors": [
                {
                    "type": "standardizedContributor",
                    "first_name": "Bruno",
                    "last_name": "Steh",
                    "name": null,
                    "headline": "Cluster Energy Coordinator, DS Smith"
                },
                {
                    "type": "nonStandardizedContributor",
                    "first_name": null,
                    "last_name": null,
                    "name": "Masa Zalaznik",
                    "headline": null
                }
            ]
        }
    ],
    "publications": [],
    "courses": [],
    "test_scores": [],
    "position_groups": [
        {
            "company": {
                "id": 3854,
                "name": "DS Smith",
                "logo": "https://media.licdn.com/dms/image/C560BAQGh1R_r16wMFA/company-logo_400_400/0/1519856141268?e=1700697600&v=beta&t=xeQ44y5N5s3CgwjIjvqBS1deofy2_wJ8CbQL3IxeEFw",
                "url": "https://www.linkedin.com/company/ds-smith/",
                "employees": {
                    "start": 10001,
                    "end": null
                }
            },
            "date": {
                "start": {
                    "month": 1,
                    "day": null,
                    "year": 2018
                },
                "end": {
                    "month": null,
                    "day": null,
                    "year": null
                }
            },
            "profile_positions": [
                {
                    "location": "Schiphol-Rijk, North Holland, Netherlands",
                    "date": {
                        "start": {
                            "month": 1,
                            "day": null,
                            "year": 2020
                        },
                        "end": {
                            "month": null,
                            "day": null,
                            "year": null
                        }
                    },
                    "company": "DS Smith",
                    "description": null,
                    "title": "Cluster Energy Coordinator",
                    "employment_type": "Full-time"
                },
                {
                    "location": "Beli\u0161ce, Osijek-Baranja, Croatia",
                    "date": {
                        "start": {
                            "month": 1,
                            "day": null,
                            "year": 2018
                        },
                        "end": {
                            "month": 12,
                            "day": null,
                            "year": 2019
                        }
                    },
                    "company": "DS Smith",
                    "description": null,
                    "title": "Graduate",
                    "employment_type": "Full-time"
                }
            ]
        },
        {
            "company": {
                "id": null,
                "name": "Sportcamp Salcher",
                "logo": null,
                "url": null,
                "employees": {
                    "start": null,
                    "end": null
                }
            },
            "date": {
                "start": {
                    "month": 5,
                    "day": null,
                    "year": 2017
                },
                "end": {
                    "month": 6,
                    "day": null,
                    "year": 2017
                }
            },
            "profile_positions": [
                {
                    "location": "Izola, Slovenia",
                    "date": {
                        "start": {
                            "month": 5,
                            "day": null,
                            "year": 2017
                        },
                        "end": {
                            "month": 6,
                            "day": null,
                            "year": 2017
                        }
                    },
                    "company": "Sportcamp Salcher",
                    "description": "\u2022 Held 1.5h tennis lessons for highschool students four times a day.\n\u2022 Teaching students how to play tennis (technique, movement, rules).",
                    "title": "Tennis Coach",
                    "employment_type": null
                }
            ]
        },
        {
            "company": {
                "id": 15250329,
                "name": "University of Ljubljana, Faculty of Electrical Engineering",
                "logo": "https://media.licdn.com/dms/image/C4D0BAQGNYSt9hYJAGA/company-logo_400_400/0/1679979459667?e=1700697600&v=beta&t=eCeBudDl9fOJRX642y0TMuV6Ht276DE25HL35SLuQEM",
                "url": "https://www.linkedin.com/school/university-of-ljubljana-electrical-engineering/",
                "employees": {
                    "start": 201,
                    "end": 500
                }
            },
            "date": {
                "start": {
                    "month": 2,
                    "day": null,
                    "year": 2017
                },
                "end": {
                    "month": 6,
                    "day": null,
                    "year": 2017
                }
            },
            "profile_positions": [
                {
                    "location": "Ljubljana",
                    "date": {
                        "start": {
                            "month": 2,
                            "day": null,
                            "year": 2017
                        },
                        "end": {
                            "month": 6,
                            "day": null,
                            "year": 2017
                        }
                    },
                    "company": "University of Ljubljana, Faculty of Electrical Engineering",
                    "description": "\u2022 Developed housing for sensor platform (that measures air quality) while taking into account all the needed requirements and desired specifications.\n\u2022 Modelling the product in SolidWorks.\n\u2022 3D printing and post processing the product.",
                    "title": "Mechanical Design Engineer",
                    "employment_type": null
                }
            ]
        },
        {
            "company": {
                "id": 6341,
                "name": "University of Ljubljana",
                "logo": "https://media.licdn.com/dms/image/C4E0BAQHdxBNw24QZXw/company-logo_400_400/0/1593587187514?e=1700697600&v=beta&t=wDnQcbU7p8MtwdAbJXOmvYDGtrq7xlXTJwtfv45ev3Y",
                "url": "https://www.linkedin.com/school/university-of-ljubljana/",
                "employees": {
                    "start": 5001,
                    "end": 10000
                }
            },
            "date": {
                "start": {
                    "month": 10,
                    "day": null,
                    "year": 2014
                },
                "end": {
                    "month": 5,
                    "day": null,
                    "year": 2015
                }
            },
            "profile_positions": [
                {
                    "location": "Ljubljana, Slovenia",
                    "date": {
                        "start": {
                            "month": 10,
                            "day": null,
                            "year": 2014
                        },
                        "end": {
                            "month": 5,
                            "day": null,
                            "year": 2015
                        }
                    },
                    "company": "University of Ljubljana",
                    "description": "\u2022\tHeld 90 minutes lectures once a week, explaining to students complex content of mathematics (vectors, functions, derivatives, integrals, matrix) and helped them with homework as part of modules Mathematica 1 and 2. \n\u2022\tIn the process gained an even better understanding of mathematics and improved skills to successfully communicate and explain difficult subjects to different types of people. \n\u2022\tClasses were successful because students that regularly took them passed their exams.",
                    "title": "Teacher Assistant",
                    "employment_type": null
                }
            ]
        },
        {
            "company": {
                "id": null,
                "name": "Danfoss",
                "logo": null,
                "url": null,
                "employees": {
                    "start": null,
                    "end": null
                }
            },
            "date": {
                "start": {
                    "month": 8,
                    "day": null,
                    "year": 2014
                },
                "end": {
                    "month": 8,
                    "day": null,
                    "year": 2014
                }
            },
            "profile_positions": [
                {
                    "location": "Ljubljana, Slovenija",
                    "date": {
                        "start": {
                            "month": 8,
                            "day": null,
                            "year": 2014
                        },
                        "end": {
                            "month": 8,
                            "day": null,
                            "year": 2014
                        }
                    },
                    "company": "Danfoss",
                    "description": "Working in a hydraulic systems laboratory doing tests on different distribution system valves (with hydraulic actuator). I set up measuring line with all pipes, valve, pressure gauges, flow meters and noise meter. I monitored experiments on HD Vision program. I measured and analysed pressure drop in certain pipes, tested two electric-motor valves if they are leaking in a close state. For another new testing site, I made an order list of pneumatic connectors from catalogues.",
                    "title": "Internship",
                    "employment_type": null
                }
            ]
        }
    ],
    "volunteer_experiences": [
        {
            "date": {
                "start": {
                    "month": 1,
                    "day": null,
                    "year": 2005
                },
                "end": {
                    "month": 9,
                    "day": null,
                    "year": 2015
                }
            },
            "role": "Leader of children holidays",
            "company": {
                "id": null,
                "name": "Mladinski svet \u010c'Bela (Youth Council)",
                "logo": null,
                "url": null
            },
            "cause": "CHILDREN",
            "description": "For the last two years, I was a leader of children holiday project, leading 35 youths to prepare holiday week for 125 children. We prepared educational theater shows, debates, all kinds of fun and educational workshops, prayers, excursions, big games,... \nI also organized different events to keep youths connected during the year and furthermore make preparation week to train them and enable them to grow personally."
        }
    ],
    "skills": [
        "Leadership",
        "Project management",
        "Personal Development",
        "Teaching Mathematics",
        "Technical Documentation",
        "Matlab",
        "Computational Fluid Dynamics (CFD)",
        "ANSYS Fluent and ICEM",
        "IPSEpro",
        "Solidworks",
        "MS Excel @risk",
        "First Aid",
        "Teamwork",
        "Quick learning",
        "Tennis",
        "Basketball",
        "PowerPoint",
        "Microsoft Excel",
        "Management",
        "Testing"
    ],
    "network_info": null,
    "related_profiles": null,
    "contact_info": null
}